{"header":"PROCESSED on Fri, 19 Dec 2025 14:50:35 +0000 from https:\/\/metaversotec.cl\/web\/web\/wp-content\/plugins\/wppu-preloader-unlimited\/public\/images\/Preloader_1.gif","files":{"wc-blocks-style":{"url":"\/wp-content\/plugins\/woocommerce\/assets\/client\/blocks\/wc-blocks.css","success":true,"version":"wc-9.9.5","last_modified":"1750724514"},"astra-addon-megamenu-dynamic":{"url":"\/wp-content\/plugins\/astra-addon\/addons\/nav-menu\/assets\/css\/minified\/magamenu-frontend.min.css","success":false,"version":"4.7.1","last_modified":"1718738744"},"jet-woo-builder":{"url":"\/wp-content\/plugins\/jet-woo-builder\/assets\/css\/frontend.css","success":true,"version":"2.1.20.1","last_modified":"1750723992"},"swiper":{"url":"\/wp-content\/plugins\/elementor\/assets\/lib\/swiper\/v8\/css\/swiper.min.css","success":true,"version":"8.4.5","last_modified":"1757966196"},"e-swiper":{"url":"\/wp-content\/plugins\/elementor\/assets\/css\/conditionals\/e-swiper.min.css","success":true,"version":"3.32.0","last_modified":"1757966195"}}}